lfp_importmap/__init__.py
lfp_importmap/apps.py
lfp_importmap/py.typed
lfp_importmap/utils.py
lfp_importmap/management/__init__.py
lfp_importmap/management/commands/__init__.py
lfp_importmap/management/commands/importmap.py
lfp_importmap/templates/lfp_importmap/javascript_importmap_tags.html
lfp_importmap/templatetags/__init__.py
lfp_importmap/templatetags/lfp_importmap.py
lfp_importmap-0.2.0.dist-info/METADATA
lfp_importmap-0.2.0.dist-info/WHEEL
lfp_importmap-0.2.0.dist-info/licenses/LICENSE
lfp_importmap-0.2.0.dist-info/RECORD
