Metadata-Version: 2.4
Name: lfp-importmap
Version: 0.2.0
Summary: Add JS importmaps to your Django project without Node or any other frontend tooling.
Project-URL: repository, https://github.com/SarthakJariwala/lfp-importmap
Author-email: Sarthak Jariwala <sarthak@sarthakjariwala.com>
License-File: LICENSE
Classifier: Development Status :: 4 - Beta
Classifier: Framework :: Django
Classifier: Intended Audience :: Developers
Classifier: License :: OSI Approved :: MIT License
Classifier: Operating System :: OS Independent
Classifier: Programming Language :: Python
Classifier: Programming Language :: Python :: 3 :: Only
Requires-Python: >=3.9
Requires-Dist: django-typer[rich]>=2.4.0
Requires-Dist: django>=4.2.16
Requires-Dist: httpx>=0.27.2
